{"options":{"validator":{"$jsonSchema":{"bsonType":"object","required":["firstName","lastName","email","phone","dateOfBirth","registrationDate"],"properties":{"firstName":{"bsonType":"string"},"lastName":{"bsonType":"string"},"email":{"bsonType":"string"},"phone":{"bsonType":"string"},"dateOfBirth":{"bsonType":"date"},"registrationDate":{"bsonType":"date"},"reservationCount":{"bsonType":"int"},"reviewCount":{"bsonType":"int"}}}}},"indexes":[{"v":{"$numberInt":"2"},"key":{"_id":{"$numberInt":"1"}},"name":"_id_"}],"uuid":"e215197b40af45eabcc74f20a30843cb","collectionName":"users","type":"collection"}